{
	"configurations" : 
	[
		{
			"directories" : 
			[
				{
					"build" : ".",
					"projectIndex" : 0,
					"source" : ".",
					"targetIndexes" : 
					[
						0,
						1
					]
				}
			],
			"name" : "Debug",
			"projects" : 
			[
				{
					"directoryIndexes" : 
					[
						0
					],
					"name" : "Epoll_socket",
					"targetIndexes" : 
					[
						0,
						1
					]
				}
			],
			"targets" : 
			[
				{
					"directoryIndex" : 0,
					"id" : "client::@6890427a1f51a3e7e1df",
					"jsonFile" : "target-client-Debug-246d91ca9c94261f4849.json",
					"name" : "client",
					"projectIndex" : 0
				},
				{
					"directoryIndex" : 0,
					"id" : "server::@6890427a1f51a3e7e1df",
					"jsonFile" : "target-server-Debug-de5002b97183e3cc2136.json",
					"name" : "server",
					"projectIndex" : 0
				}
			]
		}
	],
	"kind" : "codemodel",
	"paths" : 
	{
		"build" : "/home/sir/code/C++/Socket/project3/build",
		"source" : "/home/sir/code/C++/Socket/project3"
	},
	"version" : 
	{
		"major" : 2,
		"minor" : 0
	}
}
